[{"id":"man-0","title":"Bouncing Ball"},{"id":"man-1","title":"Coffee Can"},{"id":"man-2","title":"Counter"},{"id":"man-3","title":"Counting Machine"},{"id":"man-4","title":"Defuse Bomb"},{"id":"man-5","title":"DFA"},{"id":"man-6","title":"Einstein Riddle"},{"id":"man-7","title":"Graph"},{"id":"man-8","title":"Hamiltonian Path"},{"id":"man-9","title":"Loop Verification"},{"id":"man-10","title":"Neural Network"},{"id":"man-11","title":"Route Planning"},{"id":"man-12","title":"Swap"},{"id":"man-13","title":"Switch"},{"id":"man-14","title":"Two Bit Counter"},{"id":"man-15","title":"Zero Sum"}]