[{"title":"Compiler Options","keywords":["option","log","trace","debug","timeout","precision","detect","output"],"id":"cmp_opts","documents":[{"title":"option-debug","keywords":["debug"],"id":"debug"},{"title":"option-detect","keywords":["detect"],"id":"detect"},{"title":"option-log","keywords":["log"],"id":"log"},{"title":"option-output","keywords":["output"],"id":"output"},{"title":"option-precision","keywords":["precision"],"id":"precision"},{"title":"option-timeout","keywords":["timeout"],"id":"timeout"},{"title":"option-trace","keywords":["trace"],"id":"trace"}],"html":true},{"title":"Expressions","id":"expr","documents":[{"title":"Fresh ()","keywords":["fresh"],"id":"fresh"},{"title":"Initial ()","keywords":["initial"],"id":"initial"}]}]